flip_pose/__init__.py
flip_pose/core.py
flip_pose-0.1.0.dist-info/METADATA
flip_pose-0.1.0.dist-info/WHEEL
flip_pose-0.1.0.dist-info/licenses/LICENSE
flip_pose-0.1.0.dist-info/RECORD
